PhotoshopJiaochengBixueJiqiao/README.md
PhotoshopJiaochengBixueJiqiao/__init__.py
PhotoshopJiaochengBixueJiqiao/__main__.py
PhotoshopJiaochengBixueJiqiao/file.epub
PhotoshopJiaochengBixueJiqiao/index.html
PhotoshopJiaochengBixueJiqiao/css/__init__.py
PhotoshopJiaochengBixueJiqiao/css/annotations.css
PhotoshopJiaochengBixueJiqiao/css/main.css
PhotoshopJiaochengBixueJiqiao/css/normalize.css
PhotoshopJiaochengBixueJiqiao/css/popup.css
PhotoshopJiaochengBixueJiqiao/font/__init__.py
PhotoshopJiaochengBixueJiqiao/font/fontello.eot
PhotoshopJiaochengBixueJiqiao/font/fontello.svg
PhotoshopJiaochengBixueJiqiao/font/fontello.ttf
PhotoshopJiaochengBixueJiqiao/font/fontello.woff
PhotoshopJiaochengBixueJiqiao/img/__init__.py
PhotoshopJiaochengBixueJiqiao/img/annotator-glyph-sprite.png
PhotoshopJiaochengBixueJiqiao/img/annotator-icon-sprite.png
PhotoshopJiaochengBixueJiqiao/img/apple-touch-icon.png
PhotoshopJiaochengBixueJiqiao/img/cancelfullscreen.png
PhotoshopJiaochengBixueJiqiao/img/close.png
PhotoshopJiaochengBixueJiqiao/img/fullscreen.png
PhotoshopJiaochengBixueJiqiao/img/loader.gif
PhotoshopJiaochengBixueJiqiao/img/menu-icon.png
PhotoshopJiaochengBixueJiqiao/img/save.png
PhotoshopJiaochengBixueJiqiao/img/saved.png
PhotoshopJiaochengBixueJiqiao/img/settings-s.png
PhotoshopJiaochengBixueJiqiao/img/settings.png
PhotoshopJiaochengBixueJiqiao/img/star.png
PhotoshopJiaochengBixueJiqiao/js/__init__.py
PhotoshopJiaochengBixueJiqiao/js/epub.js
PhotoshopJiaochengBixueJiqiao/js/epub.min.js
PhotoshopJiaochengBixueJiqiao/js/epub.min.map
PhotoshopJiaochengBixueJiqiao/js/hooks.min.js
PhotoshopJiaochengBixueJiqiao/js/hooks.min.map
PhotoshopJiaochengBixueJiqiao/js/reader.js
PhotoshopJiaochengBixueJiqiao/js/reader.js.map
PhotoshopJiaochengBixueJiqiao/js/reader.min.js
PhotoshopJiaochengBixueJiqiao/js/reader.min.map
PhotoshopJiaochengBixueJiqiao/js/hooks/__init__.py
PhotoshopJiaochengBixueJiqiao/js/hooks/extensions/__init__.py
PhotoshopJiaochengBixueJiqiao/js/hooks/extensions/highlight.js
photoshop_jiaocheng_bixue_jiqiao-2024.3.2.0.dist-info/METADATA
photoshop_jiaocheng_bixue_jiqiao-2024.3.2.0.dist-info/WHEEL
photoshop_jiaocheng_bixue_jiqiao-2024.3.2.0.dist-info/entry_points.txt
photoshop_jiaocheng_bixue_jiqiao-2024.3.2.0.dist-info/top_level.txt
photoshop_jiaocheng_bixue_jiqiao-2024.3.2.0.dist-info/RECORD
